{
  "observation_mode": "event_traces",
  "time_axis_size": 128,
  "records": [
    {
      "fraction": 0.25,
      "kept_steps": 32,
      "active_test_mae": 0.002926336053082711,
      "test_mae": 0.002926336053082711
    },
    {
      "fraction": 0.5,
      "kept_steps": 64,
      "active_test_mae": 0.0028657209949540605,
      "test_mae": 0.0028657209949540605
    },
    {
      "fraction": 0.75,
      "kept_steps": 96,
      "active_test_mae": 0.0028806396369175577,
      "test_mae": 0.0028806396369175577
    },
    {
      "fraction": 1.0,
      "kept_steps": 128,
      "active_test_mae": 0.0028806396369175577,
      "test_mae": 0.0028806396369175577
    }
  ]
}