{
  "observation_mode": "event_traces",
  "time_axis_size": 128,
  "records": [
    {
      "fraction": 0.25,
      "kept_steps": 32,
      "active_test_mae": 0.0030678946470211305,
      "test_mae": 0.00306789464702113
    },
    {
      "fraction": 0.5,
      "kept_steps": 64,
      "active_test_mae": 0.0029799885368790645,
      "test_mae": 0.0029799885368790645
    },
    {
      "fraction": 0.75,
      "kept_steps": 96,
      "active_test_mae": 0.0029799885368790645,
      "test_mae": 0.0029799885368790645
    },
    {
      "fraction": 1.0,
      "kept_steps": 128,
      "active_test_mae": 0.0029799885368790645,
      "test_mae": 0.0029799885368790645
    }
  ]
}